{
  "coverage": "0%",
  "expectCount": 120,
  "actualCount": 0,
  "files": {
    "src/physics.js": {
      "expectCount": 28,
      "actualCount": 0,
      "undocumentLines": [
        22,
        57,
        70,
        64,
        80,
        7,
        21,
        24,
        12,
        11,
        18,
        19,
        14,
        13,
        16,
        17,
        10,
        15,
        25,
        81,
        44,
        46,
        29,
        26,
        28,
        32,
        30,
        27
      ]
    },
    "src/index.js": {
      "expectCount": 60,
      "actualCount": 0,
      "undocumentLines": [
        10,
        4,
        20,
        14,
        16,
        17,
        18,
        153,
        43,
        11,
        3,
        52,
        168,
        104,
        231,
        51,
        169,
        44,
        154,
        21,
        35,
        258,
        58,
        7,
        80,
        180,
        121,
        200,
        171,
        123,
        50,
        155,
        23,
        216,
        157,
        158,
        160,
        22,
        26,
        156,
        5,
        188,
        24,
        49,
        262,
        254,
        73,
        54,
        193,
        159,
        125,
        33,
        65,
        126,
        68,
        173,
        98,
        122,
        162,
        165
      ]
    },
    "src/view.js": {
      "expectCount": 32,
      "actualCount": 0,
      "undocumentLines": [
        4,
        3,
        6,
        49,
        145,
        134,
        62,
        36,
        100,
        108,
        15,
        29,
        7,
        122,
        90,
        160,
        73,
        76,
        26,
        124,
        17,
        137,
        44,
        59,
        68,
        33,
        9,
        69,
        8,
        123,
        128,
        151
      ]
    }
  }
}